strongdoc/__about__.py
strongdoc/__init__.py
strongdoc/client.py
strongdoc/constants.py
strongdoc/api/__init__.py
strongdoc/api/account.py
strongdoc/api/billing.py
strongdoc/api/document.py
strongdoc/api/login.py
strongdoc/api/search.py
strongdoc/data/certs/grpc.root.localhost.pem
strongdoc/data/certs/grpc.root.pem
strongdoc/proto/__init__.py
strongdoc/proto/accounts_pb2.py
strongdoc/proto/accounts_pb2_grpc.py
strongdoc/proto/billing_pb2.py
strongdoc/proto/billing_pb2_grpc.py
strongdoc/proto/documentNoStore_pb2.py
strongdoc/proto/documentNoStore_pb2_grpc.py
strongdoc/proto/document_pb2.py
strongdoc/proto/document_pb2_grpc.py
strongdoc/proto/search_pb2.py
strongdoc/proto/search_pb2_grpc.py
strongdoc/proto/strongdoc_pb2.py
strongdoc/proto/strongdoc_pb2_grpc.py
strongdoc/proto/google/__init__.py
strongdoc/proto/google/api/__init__.py
strongdoc/proto/google/api/annotations_pb2.py
strongdoc/proto/google/api/annotations_pb2_grpc.py
strongdoc/proto/google/api/http_pb2.py
strongdoc/proto/google/api/http_pb2_grpc.py
strongdoc/proto/google/api/httpbody_pb2.py
strongdoc/proto/google/api/httpbody_pb2_grpc.py
strongdoc/proto/protoc_gen_swagger/__init__.py
strongdoc/proto/protoc_gen_swagger/options/__init__.py
strongdoc/proto/protoc_gen_swagger/options/annotations_pb2.py
strongdoc/proto/protoc_gen_swagger/options/annotations_pb2_grpc.py
strongdoc/proto/protoc_gen_swagger/options/openapiv2_pb2.py
strongdoc/proto/protoc_gen_swagger/options/openapiv2_pb2_grpc.py
strongsalt_strongdoc_python_sdk-0.0.10.dist-info/LICENSE.txt
strongsalt_strongdoc_python_sdk-0.0.10.dist-info/METADATA
strongsalt_strongdoc_python_sdk-0.0.10.dist-info/WHEEL
strongsalt_strongdoc_python_sdk-0.0.10.dist-info/top_level.txt
strongsalt_strongdoc_python_sdk-0.0.10.dist-info/RECORD
