Metadata-Version: 2.1
Name: strongsalt-strongdoc-python-sdk
Version: 0.0.10
Summary: The StrongDoc Python SDK for interacting with the StrongDoc API.
Home-page: https://github.com/overnest/strongdoc-python-sdk
Author: StrongDoc
Author-email: info@strongsalt.com
License: LICENSE.txt
Platform: UNKNOWN
Classifier: Operating System :: OS Independent
Classifier: Topic :: Security
Classifier: Operating System :: POSIX
Classifier: Operating System :: Microsoft :: Windows
Classifier: Operating System :: MacOS :: MacOS X
Classifier: Topic :: Software Development :: Libraries :: Python Modules
Requires-Python: >=3.6
Requires-Dist: pathlib
Requires-Dist: grpcio
Requires-Dist: protobuf
Requires-Dist: six
